fundb/__init__.py
fundb/json/__init__.py
fundb/json/jsonextendsclass.py
fundb/sqlalchemy/__init__.py
fundb/sqlalchemy/base.py
fundb/sqlalchemy/engine.py
farfundb-1.2.6.dist-info/LICENSE
farfundb-1.2.6.dist-info/METADATA
farfundb-1.2.6.dist-info/WHEEL
farfundb-1.2.6.dist-info/top_level.txt
farfundb-1.2.6.dist-info/RECORD
