Metadata-Version: 2.1
Name: farfundb
Version: 1.2.6
Summary: Add your description here
Requires-Python: >=3.7
License-File: LICENSE
Requires-Dist: sqlalchemy >=2.0.36
